setup.py
JsonUtils.egg-info/PKG-INFO
JsonUtils.egg-info/SOURCES.txt
JsonUtils.egg-info/dependency_links.txt
JsonUtils.egg-info/top_level.txt
jsonutils/__init__.py
jsonutils/json.py
jsonutils/jsonrpc.py
jsonutils/minjson.py
