Metadata-Version: 1.0
Name: JsonUtils
Version: 0.1
Summary: jsonutils, a JSON parser and JSON-RPC handler.
Home-page: http://atlas.nmfs.hawaii.edu
Author: Russell Moffitt
Author-email: Russell.Moffitt@noaa.gov
License: GPL
Keywords: json jsonrpc,json-rpc,jsonutils,rpc,javascript,xml,webservice
Platform: UNKNOWN
